mdx_noop.py
mdx_noop-0.0.2.dist-info/LICENSE.txt
mdx_noop-0.0.2.dist-info/METADATA
mdx_noop-0.0.2.dist-info/WHEEL
mdx_noop-0.0.2.dist-info/top_level.txt
mdx_noop-0.0.2.dist-info/RECORD
