Metadata-Version: 2.1
Name: mdx-noop
Version: 0.0.2
Summary: Markdown extension to add "noop" formatting directives
Author-email: Fabian Geiselhart <me@f4814n.de>
License: MIT License
Project-URL: Homepage, https://github.com/f4814/mdx_noop
Project-URL: Bug Tracker, https://github.com/f4814/mdx_noop/issues
Classifier: Programming Language :: Python
Classifier: Intended Audience :: Developers
Classifier: License :: OSI Approved :: MIT License
Classifier: Operating System :: OS Independent
Requires-Python: >=3.7
License-File: LICENSE.txt
Requires-Dist: markdown
